spmsimu/__init__.py
spmsimu/simulator.py
spmsimu-0.0.2.dist-info/LICENSE
spmsimu-0.0.2.dist-info/METADATA
spmsimu-0.0.2.dist-info/WHEEL
spmsimu-0.0.2.dist-info/top_level.txt
spmsimu-0.0.2.dist-info/RECORD
